Workbook

Sheet Read Me
A1: Revenue Recognition Workbook — How This Is Organized
A3: Tab | B3: Purpose
A4: Campaigns | B4: One row per overarching campaign budget. Shows the total budget, how much is allocated to sub-projects/SOWs so far, how much is earned/open, and — for flex budgets — how much is still available to move to a different sub-project within that same campaign.
A5: Sub-Projects (SOWs) | B5: One row per SOW or task line, each tied to a Campaign ID. Earned-to-date and Open pull automatically from the Monthly Recognition tab, so you no longer total months by hand.
A6: Monthly Recognition | B6: One row per month per SOW (long format instead of a 20-column-wide grid). Adding a new month is just adding new rows — no need to insert columns across every campaign block. Each row also tags the invoice number tied to that revenue.
A7: Invoices - Finance | B7: The list you hand to Finance: invoice number, campaign, SOW, amount, and status (sent / not sent / confirmed). Filter to 'Not Yet Sent' each period to see exactly what still needs to go to Finance.
A9: Color key
A10: Blue text | B10: Editable input — type or change these directly.
A11: Black text | B11: Formula — calculated automatically, don't overwrite.
A12: Yellow highlight | B12: Data-quality flag carried over from your original file — needs a decision from you.
A14: Data-quality flags found in your original file
A15: Duplicate Campaign ID | B15: "Campaign UCMC-010" was used for both Strategic Counsel & Advisory Support and Comms AOR. Split into CMP-06 and CMP-07 here — confirm whether they should actually share one flex pool or stay separate.
A16: Comms AOR has no top-level budget | B16: The original file never set an Original/Revised Budget for the Comms AOR campaign header. This workbook backed into $240,000 from the known monthly invoices — confirm the real approved budget.
A17: Landing Page Design (26-UCMC-050) has no budget | B17: Only a $1,032.50 earned amount exists for this SOW; Original Budget was blank in your file. Flagged for you to fill in.
A18: OOP Expense line with no invoice number | B18: Comms AOR's May OOP Expense ($6,278.58) has no invoice reference in the source file, unlike the March OOP line which cites INV-39804AO.
A19: Service Line Campaigns has no sub-projects | B19: The campaign header exists with a $0 budget but no SOWs were ever itemized under it.
A20: Broken reference errors in original file | B20: Cancer Center Pavilion and Haas F1 Partnership had broken-reference (REF) errors in the Revised Budget column of your original workbook — rebuilt from scratch here.
A21: Most revenue has no invoice # tied to it | B21: Only Haas F1 Partnership and Comms AOR embed invoice numbers in your original file. The other 5 campaigns have never had an invoice number captured against the revenue — see the Invoices - Finance tab.

Sheet Campaigns
A1: Campaign ID | B1: Campaign Name | C1: Flex? | D1: Original Budget | E1: Revised Budget | F1: Allocated to Sub-Projects | G1: Available to Reallocate (Flex) | H1: Total Earned | I1: Total Open | J1: Notes
A2: CMP-01 | B2: Brand Campaign Creative | C2: Y | D2: 2015000 | E2: 2015000 | F2: =SUMIF('Sub-Projects (SOWs)'!$B$2:$B$40,$A2,'Sub-Projects (SOWs)'!$F$2:$F$40) -> 2015000 | G2: =E2-F2 -> 0 | H2: =SUMIF('Sub-Projects (SOWs)'!$B$2:$B$40,$A2,'Sub-Projects (SOWs)'!$G$2:$G$40) -> 236349.75 | I2: =E2-H2 -> 1778650.2 | J2: Original UCMC-004.
A3: CMP-02 | B3: Service Line Campaigns | C3: Y | D3: 0 | E3: 0 | F3: =SUMIF('Sub-Projects (SOWs)'!$B$2:$B$40,$A3,'Sub-Projects (SOWs)'!$F$2:$F$40) -> 0 | G3: =E3-F3 -> 0 | H3: =SUMIF('Sub-Projects (SOWs)'!$B$2:$B$40,$A3,'Sub-Projects (SOWs)'!$G$2:$G$40) -> 0 | I3: =E3-H3 -> 0 | J3: UCMC-006. No sub-projects defined yet in source file.
A4: CMP-03 | B4: Cancer Center Pavilion | C4: Y | D4: 2215000 | E4: 2215000 | F4: =SUMIF('Sub-Projects (SOWs)'!$B$2:$B$40,$A4,'Sub-Projects (SOWs)'!$F$2:$F$40) -> 2215000 | G4: =E4-F4 -> 0 | H4: =SUMIF('Sub-Projects (SOWs)'!$B$2:$B$40,$A4,'Sub-Projects (SOWs)'!$G$2:$G$40) -> 256086.25 | I4: =E4-H4 -> 1958913.8 | J4: Includes standalone SOW 25-UCMC-200 plus the UCMC-007 sub-project group. Original file had no usable top-level budget (broken reference error) — this total is reconstructed as the sum of its sub-projects. Confirm the real approved campaign budget.
A5: CMP-04 | B5: U.S. News & World Report Voting/Reputation | C5: Y | D5: 528000 | E5: 528000 | F5: =SUMIF('Sub-Projects (SOWs)'!$B$2:$B$40,$A5,'Sub-Projects (SOWs)'!$F$2:$F$40) -> 528000 | G5: =E5-F5 -> 0 | H5: =SUMIF('Sub-Projects (SOWs)'!$B$2:$B$40,$A5,'Sub-Projects (SOWs)'!$G$2:$G$40) -> 514000 | I5: =E5-H5 -> 14000
A6: CMP-05 | B6: Haas F1 Partnership | C6: Y | D6: 247250 | E6: 247250 | F6: =SUMIF('Sub-Projects (SOWs)'!$B$2:$B$40,$A6,'Sub-Projects (SOWs)'!$F$2:$F$40) -> 247250 | G6: =E6-F6 -> 0 | H6: =SUMIF('Sub-Projects (SOWs)'!$B$2:$B$40,$A6,'Sub-Projects (SOWs)'!$G$2:$G$40) -> 122500 | I6: =E6-H6 -> 124750 | J6: UCMC-009. Invoiced monthly.
A7: CMP-06 | B7: Strategic Counsel & Advisory Support | C7: Y | D7: 490000 | E7: 490000 | F7: =SUMIF('Sub-Projects (SOWs)'!$B$2:$B$40,$A7,'Sub-Projects (SOWs)'!$F$2:$F$40) -> 490000 | G7: =E7-F7 -> 0 | H7: =SUMIF('Sub-Projects (SOWs)'!$B$2:$B$40,$A7,'Sub-Projects (SOWs)'!$G$2:$G$40) -> 116159.3 | I7: =E7-H7 -> 373840.7 | J7: UCMC-010.
A8: CMP-07 | B8: Comms AOR | C8: Y | D8: 255153.5 | E8: 255153.5 | F8: =SUMIF('Sub-Projects (SOWs)'!$B$2:$B$40,$A8,'Sub-Projects (SOWs)'!$F$2:$F$40) -> 255153.5 | G8: =E8-F8 -> 0 | H8: =SUMIF('Sub-Projects (SOWs)'!$B$2:$B$40,$A8,'Sub-Projects (SOWs)'!$G$2:$G$40) -> 195153.5 | I8: =E8-H8 -> 60000 | J8: Also referenced as UCMC-010 in source file (duplicate ID) — no top-level budget was set originally; reconstructed as the sum of known invoices. Confirm real contracted budget.
B9: TOTAL | D9: =SUM(D2:D8) -> 5750403.5 | E9: =SUM(E2:E8) -> 5750403.5 | F9: =SUM(F2:F8) -> 5750403.5 | G9: =SUM(G2:G8) -> 0 | H9: =SUM(H2:H8) -> 1440248.8 | I9: =SUM(I2:I8) -> 4310154.7

Sheet Sub-Projects (SOWs)
A1: SOW/Task ID | B1: Campaign ID | C1: Legacy Group Ref | D1: Description | E1: Original Budget | F1: Revised Budget | G1: Earned to Date | H1: Open | I1: Status | J1: Notes
A2: 25-UCMC-016 | B2: CMP-01 | C2: UCMC-004 | D2: Branding Campaign - Concepting | E2: 300000 | F2: 300000 | G2: =SUMIF('Monthly Recognition'!$A$2:$A$100,$A2,'Monthly Recognition'!$E$2:$E$100) -> 221349.75 | H2: =F2-G2 -> 78650.25 | I2: In Progress
A3: 25-UCMC-018 | B3: CMP-01 | C3: UCMC-004 | D3: Forecasted - Brand Campaign Deliverables | E3: 700000 | F3: 700000 | G3: =SUMIF('Monthly Recognition'!$A$2:$A$100,$A3,'Monthly Recognition'!$E$2:$E$100) -> 0 | H3: =F3-G3 -> 700000 | I3: Not Started
A4: 25-UCMC-019 | B4: CMP-01 | C4: UCMC-004 | D4: Branding Campaign - Video/Photoshoot | E4: 1000000 | F4: 1000000 | G4: =SUMIF('Monthly Recognition'!$A$2:$A$100,$A4,'Monthly Recognition'!$E$2:$E$100) -> 0 | H4: =F4-G4 -> 1000000 | I4: Not Started
A5: 25-UCMC-023 | B5: CMP-01 | C5: UCMC-004 | D5: Brand Campaign Concept Testing | E5: 15000 | F5: 15000 | G5: =SUMIF('Monthly Recognition'!$A$2:$A$100,$A5,'Monthly Recognition'!$E$2:$E$100) -> 15000 | H5: =F5-G5 -> 0 | I5: Complete
A6: 25-UCMC-200 | B6: CMP-03 | C6: (direct) | D6: Cancer Pavilion Plan | E6: 125000 | F6: 125000 | G6: =SUMIF('Monthly Recognition'!$A$2:$A$100,$A6,'Monthly Recognition'!$E$2:$E$100) -> 125000 | H6: =F6-G6 -> 0 | I6: In Progress
A7: 26-UCMC-047 | B7: CMP-03 | C7: UCMC-007 | D7: Creative Concepting | E7: 175000 | F7: 175000 | G7: =SUMIF('Monthly Recognition'!$A$2:$A$100,$A7,'Monthly Recognition'!$E$2:$E$100) -> 54351.25 | H7: =F7-G7 -> 120648.75 | I7: In Progress
A8: CMP3-EXTRA1 | B8: CMP-03 | C8: UCMC-007 | D8: Creative Development & Production | E8: 450000 | F8: 450000 | G8: =SUMIF('Monthly Recognition'!$A$2:$A$100,$A8,'Monthly Recognition'!$E$2:$E$100) -> 0 | H8: =F8-G8 -> 450000 | I8: Not Started | J8: No SOW code in source file.
A9: 26-UCMC-050 | B9: CMP-03 | C9: UCMC-007 | D9: Landing Page Design | E9: 0 | F9: 0 | G9: =SUMIF('Monthly Recognition'!$A$2:$A$100,$A9,'Monthly Recognition'!$E$2:$E$100) -> 1032.5 | H9: =F9-G9 -> -1032.5 | I9: In Progress | J9: No Original Budget in source file — confirm amount.
A10: 26-UCMC-036 | B10: CMP-03 | C10: UCMC-007 | D10: Integrated Engagement Strategy & Plan | E10: 85000 | F10: 85000 | G10: =SUMIF('Monthly Recognition'!$A$2:$A$100,$A10,'Monthly Recognition'!$E$2:$E$100) -> 10001.25 | H10: =F10-G10 -> 74998.75 | I10: In Progress
A11: 26-UCMC-037 | B11: CMP-03 | C11: UCMC-007 | D11: Program Governance Meetings | E11: 65000 | F11: 65000 | G11: =SUMIF('Monthly Recognition'!$A$2:$A$100,$A11,'Monthly Recognition'!$E$2:$E$100) -> 970 | H11: =F11-G11 -> 64030 | I11: In Progress
A12: 26-UCMC-040 | B12: CMP-03 | C12: UCMC-007 | D12: SEO Strategy & Optimization | E12: 50000 | F12: 50000 | G12: =SUMIF('Monthly Recognition'!$A$2:$A$100,$A12,'Monthly Recognition'!$E$2:$E$100) -> 0 | H12: =F12-G12 -> 50000 | I12: Not Started
A13: 26-UCMC-041 | B13: CMP-03 | C13: UCMC-007 | D13: Earned Media | E13: 25000 | F13: 25000 | G13: =SUMIF('Monthly Recognition'!$A$2:$A$100,$A13,'Monthly Recognition'!$E$2:$E$100) -> 0 | H13: =F13-G13 -> 25000 | I13: Not Started
A14: 26-UCMC-038 | B14: CMP-03 | C14: UCMC-007 | D14: Paid Media Expenses | E14: 434625 | F14: 434625 | G14: =SUMIF('Monthly Recognition'!$A$2:$A$100,$A14,'Monthly Recognition'!$E$2:$E$100) -> 0 | H14: =F14-G14 -> 434625 | I14: Not Started
A15: 26-UCMC-039 | B15: CMP-03 | C15: UCMC-007 | D15: Paid Media Labor & Measurement | E15: 40375 | F15: 40375 | G15: =SUMIF('Monthly Recognition'!$A$2:$A$100,$A15,'Monthly Recognition'!$E$2:$E$100) -> 0 | H15: =F15-G15 -> 40375 | I15: Not Started
A16: 26-UCMC-042 | B16: CMP-03 | C16: UCMC-007 | D16: Event Planning | E16: 250000 | F16: 250000 | G16: =SUMIF('Monthly Recognition'!$A$2:$A$100,$A16,'Monthly Recognition'!$E$2:$E$100) -> 4342.5 | H16: =F16-G16 -> 245657.5 | I16: In Progress
A17: 26-UCMC-043 | B17: CMP-03 | C17: UCMC-007 | D17: Event Travel OOP Expenses | E17: 15000 | F17: 15000 | G17: =SUMIF('Monthly Recognition'!$A$2:$A$100,$A17,'Monthly Recognition'!$E$2:$E$100) -> 0 | H17: =F17-G17 -> 15000 | I17: Not Started
A18: 26-UCMC-044 | B18: CMP-03 | C18: UCMC-007 | D18: Community Engagement | E18: 50000 | F18: 50000 | G18: =SUMIF('Monthly Recognition'!$A$2:$A$100,$A18,'Monthly Recognition'!$E$2:$E$100) -> 3496.25 | H18: =F18-G18 -> 46503.75 | I18: In Progress
A19: 26-UCMC-029 | B19: CMP-03 | C19: UCMC-007 | D19: Account Management & Advisory | E19: 225000 | F19: 225000 | G19: =SUMIF('Monthly Recognition'!$A$2:$A$100,$A19,'Monthly Recognition'!$E$2:$E$100) -> 56892.5 | H19: =F19-G19 -> 168107.5 | I19: In Progress
A20: CMP3-EXTRA2 | B20: CMP-03 | C20: UCMC-007 | D20: Event Production & Vendor Estimated Hard Cost | E20: 225000 | F20: 225000 | G20: =SUMIF('Monthly Recognition'!$A$2:$A$100,$A20,'Monthly Recognition'!$E$2:$E$100) -> 0 | H20: =F20-G20 -> 225000 | I20: Not Started | J20: No SOW code in source file.
A21: 25-UCMC-021 | B21: CMP-04 | C21: (direct) | D21: U.S. News & World Report Voting Campaign | E21: 440000 | F21: 440000 | G21: =SUMIF('Monthly Recognition'!$A$2:$A$100,$A21,'Monthly Recognition'!$E$2:$E$100) -> 440000 | H21: =F21-G21 -> 0 | I21: Complete
A22: 26-UCMC-035 | B22: CMP-04 | C22: (direct) | D22: UChicago National Reputation Campaign - Conference Support | E22: 88000 | F22: 88000 | G22: =SUMIF('Monthly Recognition'!$A$2:$A$100,$A22,'Monthly Recognition'!$E$2:$E$100) -> 74000 | H22: =F22-G22 -> 14000 | I22: In Progress
A23: CMP5-SOW1 | B23: CMP-05 | C23: UCMC-009 | D23: Haas F1 Partnership: Overall Strategic Support | E23: 247250 | F23: 247250 | G23: =SUMIF('Monthly Recognition'!$A$2:$A$100,$A23,'Monthly Recognition'!$E$2:$E$100) -> 122500 | H23: =F23-G23 -> 124750 | I23: In Progress | J23: Invoiced monthly — see Invoices - Finance tab for the 12 monthly invoice lines.
A24: 25-UCMC-001 | B24: CMP-06 | C24: UCMC-010 | D24: UChicago Account Oversight | E24: 310000 | F24: 310000 | G24: =SUMIF('Monthly Recognition'!$A$2:$A$100,$A24,'Monthly Recognition'!$E$2:$E$100) -> 115000 | H24: =F24-G24 -> 195000 | I24: In Progress
A25: CMP6-EXTRA1 | B25: CMP-06 | C25: UCMC-010 | D25: OOP Expenses | E25: 30000 | F25: 30000 | G25: =SUMIF('Monthly Recognition'!$A$2:$A$100,$A25,'Monthly Recognition'!$E$2:$E$100) -> 1159.3 | H25: =F25-G25 -> 28840.7 | I25: In Progress | J25: No SOW code in source file.
A26: CMP6-EXTRA2 | B26: CMP-06 | C26: UCMC-010 | D26: Annual Planning | E26: 150000 | F26: 150000 | G26: =SUMIF('Monthly Recognition'!$A$2:$A$100,$A26,'Monthly Recognition'!$E$2:$E$100) -> 0 | H26: =F26-G26 -> 150000 | I26: Not Started
A27: CMP7-SOW1 | B27: CMP-07 | C27: UCMC-010 (dup) | D27: Comms AOR Retainer | E27: 240000 | F27: 240000 | G27: =SUMIF('Monthly Recognition'!$A$2:$A$100,$A27,'Monthly Recognition'!$E$2:$E$100) -> 180000 | H27: =F27-G27 -> 60000 | I27: In Progress | J27: Budget backed into from known monthly invoices — confirm actual contracted amount.
A28: CMP7-EXTRA1 | B28: CMP-07 | C28: UCMC-010 (dup) | D28: OOP Expenses | E28: 15153.5 | F28: 15153.5 | G28: =SUMIF('Monthly Recognition'!$A$2:$A$100,$A28,'Monthly Recognition'!$E$2:$E$100) -> 15153.5 | H28: =F28-G28 -> 0 | I28: In Progress | J28: Budget backed into from known monthly invoices — confirm actual contracted amount.

Sheet Monthly Recognition
A1: SOW/Task ID | B1: Campaign ID | C1: Month | D1: Type | E1: Amount | F1: Invoice # | G1: Recognized? | H1: Notes
A2: 25-UCMC-016 | B2: =INDEX('Sub-Projects (SOWs)'!$B$2:$B$40,MATCH($A2,'Sub-Projects (SOWs)'!$A$2:$A$40,0)) -> CMP-01 | C2: Nov-25 | D2: Fee | E2: 75003 | F2: Not yet assigned | G2: Y
A3: 25-UCMC-016 | B3: =INDEX('Sub-Projects (SOWs)'!$B$2:$B$40,MATCH($A3,'Sub-Projects (SOWs)'!$A$2:$A$40,0)) -> CMP-01 | C3: Dec-25 | D3: Fee | E3: 75000 | F3: Not yet assigned | G3: Y
A4: 25-UCMC-016 | B4: =INDEX('Sub-Projects (SOWs)'!$B$2:$B$40,MATCH($A4,'Sub-Projects (SOWs)'!$A$2:$A$40,0)) -> CMP-01 | C4: Jan-26 | D4: Fee | E4: 70746.75 | F4: Not yet assigned | G4: Y
A5: 25-UCMC-016 | B5: =INDEX('Sub-Projects (SOWs)'!$B$2:$B$40,MATCH($A5,'Sub-Projects (SOWs)'!$A$2:$A$40,0)) -> CMP-01 | C5: Feb-26 | D5: Fee | E5: 600 | F5: Not yet assigned | G5: Y
A6: 25-UCMC-023 | B6: =INDEX('Sub-Projects (SOWs)'!$B$2:$B$40,MATCH($A6,'Sub-Projects (SOWs)'!$A$2:$A$40,0)) -> CMP-01 | C6: Dec-25 | D6: Fee | E6: 9000 | F6: Not yet assigned | G6: Y
A7: 25-UCMC-023 | B7: =INDEX('Sub-Projects (SOWs)'!$B$2:$B$40,MATCH($A7,'Sub-Projects (SOWs)'!$A$2:$A$40,0)) -> CMP-01 | C7: Jan-26 | D7: Fee | E7: 6000 | F7: Not yet assigned | G7: Y
A8: 25-UCMC-200 | B8: =INDEX('Sub-Projects (SOWs)'!$B$2:$B$40,MATCH($A8,'Sub-Projects (SOWs)'!$A$2:$A$40,0)) -> CMP-03 | C8: Nov-25 | D8: Fee | E8: 62500 | F8: Not yet assigned | G8: Y
A9: 25-UCMC-200 | B9: =INDEX('Sub-Projects (SOWs)'!$B$2:$B$40,MATCH($A9,'Sub-Projects (SOWs)'!$A$2:$A$40,0)) -> CMP-03 | C9: Dec-25 | D9: Fee | E9: 62500 | F9: Not yet assigned | G9: Y
A10: 26-UCMC-047 | B10: =INDEX('Sub-Projects (SOWs)'!$B$2:$B$40,MATCH($A10,'Sub-Projects (SOWs)'!$A$2:$A$40,0)) -> CMP-03 | C10: Apr-26 | D10: Fee | E10: 1443.75 | F10: Not yet assigned | G10: Y
A11: 26-UCMC-047 | B11: =INDEX('Sub-Projects (SOWs)'!$B$2:$B$40,MATCH($A11,'Sub-Projects (SOWs)'!$A$2:$A$40,0)) -> CMP-03 | C11: May-26 | D11: Fee | E11: 52907.5 | F11: Not yet assigned | G11: Y
A12: 26-UCMC-050 | B12: =INDEX('Sub-Projects (SOWs)'!$B$2:$B$40,MATCH($A12,'Sub-Projects (SOWs)'!$A$2:$A$40,0)) -> CMP-03 | C12: May-26 | D12: Fee | E12: 1032.5 | F12: Not yet assigned | G12: Y
A13: 26-UCMC-036 | B13: =INDEX('Sub-Projects (SOWs)'!$B$2:$B$40,MATCH($A13,'Sub-Projects (SOWs)'!$A$2:$A$40,0)) -> CMP-03 | C13: Apr-26 | D13: Fee | E13: 246.25 | F13: Not yet assigned | G13: Y
... A26: 26-UCMC-035 | B26: =INDEX('Sub-Projects (SOWs)'!$B$2:$B$40,MATCH($A26,'Sub-Projects (SOWs)'!$A$2:$A$40,0)) -> CMP-04 | C26: May-26 | D26: Fee | E26: 52000 | F26: Not yet assigned | G26: Y
A27: CMP5-SOW1 | B27: =INDEX('Sub-Projects (SOWs)'!$B$2:$B$40,MATCH($A27,'Sub-Projects (SOWs)'!$A$2:$A$40,0)) -> CMP-05 | C27: Jan-26 | D27: Fee | E27: 19500 | F27: INV-38952AF | G27: Y | H27: Jan Advisory/shot list
A28: CMP5-SOW1 | B28: =INDEX('Sub-Projects (SOWs)'!$B$2:$B$40,MATCH($A28,'Sub-Projects (SOWs)'!$A$2:$A$40,0)) -> CMP-05 | C28: Feb-26 | D28: Fee | E28: 14500 | F28: INV-38953AF | G28: Y | H28: Feb Advisory/Landing pg/Social
A29: CMP5-SOW1 | B29: =INDEX('Sub-Projects (SOWs)'!$B$2:$B$40,MATCH($A29,'Sub-Projects (SOWs)'!$A$2:$A$40,0)) -> CMP-05 | C29: Apr-26 | D29: Fee | E29: 30000 | F29: INV-38953AF | G29: Y | H29: Remainder of Feb invoice, recognized in April per source file
A30: CMP5-SOW1 | B30: =INDEX('Sub-Projects (SOWs)'!$B$2:$B$40,MATCH($A30,'Sub-Projects (SOWs)'!$A$2:$A$40,0)) -> CMP-05 | C30: Mar-26 | D30: Fee | E30: 14500 | F30: INV-39386AF | G30: Y | H30: March
A31: CMP5-SOW1 | B31: =INDEX('Sub-Projects (SOWs)'!$B$2:$B$40,MATCH($A31,'Sub-Projects (SOWs)'!$A$2:$A$40,0)) -> CMP-05 | C31: Apr-26 | D31: Fee | E31: 21500 | F31: INV-39927AF | G31: Y | H31: April Advisory
A32: CMP5-SOW1 | B32: =INDEX('Sub-Projects (SOWs)'!$B$2:$B$40,MATCH($A32,'Sub-Projects (SOWs)'!$A$2:$A$40,0)) -> CMP-05 | C32: May-26 | D32: Fee | E32: 22500 | F32: INV-40021AF | G32: Y | H32: May Advisory
A33: 25-UCMC-001 | B33: =INDEX('Sub-Projects (SOWs)'!$B$2:$B$40,MATCH($A33,'Sub-Projects (SOWs)'!$A$2:$A$40,0)) -> CMP-06 | C33: Nov-25 | D33: Fee | E33: 15000 | F33: Not yet assigned | G33: Y
A34: 25-UCMC-001 | B34: =INDEX('Sub-Projects (SOWs)'!$B$2:$B$40,MATCH($A34,'Sub-Projects (SOWs)'!$A$2:$A$40,0)) -> CMP-06 | C34: Dec-25 | D34: Fee | E34: 15000 | F34: Not yet assigned | G34: Y
A35: 25-UCMC-001 | B35: =INDEX('Sub-Projects (SOWs)'!$B$2:$B$40,MATCH($A35,'Sub-Projects (SOWs)'!$A$2:$A$40,0)) -> CMP-06 | C35: Jan-26 | D35: Fee | E35: 20000 | F35: Not yet assigned | G35: Y
A36: 25-UCMC-001 | B36: =INDEX('Sub-Projects (SOWs)'!$B$2:$B$40,MATCH($A36,'Sub-Projects (SOWs)'!$A$2:$A$40,0)) -> CMP-06 | C36: Feb-26 | D36: Fee | E36: 20000 | F36: Not yet assigned | G36: Y
A37: 25-UCMC-001 | B37: =INDEX('Sub-Projects (SOWs)'!$B$2:$B$40,MATCH($A37,'Sub-Projects (SOWs)'!$A$2:$A$40,0)) -> CMP-06 | C37: Mar-26 | D37: Fee | E37: 15000 | F37: Not yet assigned | G37: Y
A38: 25-UCMC-001 | B38: =INDEX('Sub-Projects (SOWs)'!$B$2:$B$40,MATCH($A38,'Sub-Projects (SOWs)'!$A$2:$A$40,0)) -> CMP-06 | C38: Apr-26 | D38: Fee | E38: 15000 | F38: Not yet assigned | G38: Y
A39: 25-UCMC-001 | B39: =INDEX('Sub-Projects (SOWs)'!$B$2:$B$40,MATCH($A39,'Sub-Projects (SOWs)'!$A$2:$A$40,0)) -> CMP-06 | C39: May-26 | D39: Fee | E39: 15000 | F39: Not yet assigned | G39: Y
A40: CMP6-EXTRA1 | B40: =INDEX('Sub-Projects (SOWs)'!$B$2:$B$40,MATCH($A40,'Sub-Projects (SOWs)'!$A$2:$A$40,0)) -> CMP-06 | C40: Apr-26 | D40: Expense | E40: 650 | F40: Not yet assigned | G40: Y | H40: OOP Expenses
A41: CMP6-EXTRA1 | B41: =INDEX('Sub-Projects (SOWs)'!$B$2:$B$40,MATCH($A41,'Sub-Projects (SOWs)'!$A$2:$A$40,0)) -> CMP-06 | C41: May-26 | D41: Expense | E41: 509.3 | F41: Not yet assigned | G41: Y | H41: OOP Expenses
A42: CMP7-SOW1 | B42: =INDEX('Sub-Projects (SOWs)'!$B$2:$B$40,MATCH($A42,'Sub-Projects (SOWs)'!$A$2:$A$40,0)) -> CMP-07 | C42: Mar-26 | D42: Fee | E42: 60000 | F42: INV-37370AF | G42: Y
A43: CMP7-SOW1 | B43: =INDEX('Sub-Projects (SOWs)'!$B$2:$B$40,MATCH($A43,'Sub-Projects (SOWs)'!$A$2:$A$40,0)) -> CMP-07 | C43: Apr-26 | D43: Fee | E43: 60000 | F43: INV-37371AF | G43: Y
A44: CMP7-SOW1 | B44: =INDEX('Sub-Projects (SOWs)'!$B$2:$B$40,MATCH($A44,'Sub-Projects (SOWs)'!$A$2:$A$40,0)) -> CMP-07 | C44: May-26 | D44: Fee | E44: 60000 | F44: INV-37372AF | G44: Y
A45: CMP7-EXTRA1 | B45: =INDEX('Sub-Projects (SOWs)'!$B$2:$B$40,MATCH($A45,'Sub-Projects (SOWs)'!$A$2:$A$40,0)) -> CMP-07 | C45: Mar-26 | D45: Expense | E45: 8874.92 | F45: INV-39804AO | G45: Y | H45: OOP Expenses
A46: CMP7-EXTRA1 | B46: =INDEX('Sub-Projects (SOWs)'!$B$2:$B$40,MATCH($A46,'Sub-Projects (SOWs)'!$A$2:$A$40,0)) -> CMP-07 | C46: May-26 | D46: Fee | E46: 6278.58 | F46: Not yet assigned | G46: Y | H46: OOP Expenses — no invoice # in source file

Sheet Invoices - Finance
A1: Invoice # | B1: Campaign | C1: SOW/Task ID(s) | D1: Period | E1: Amount | F1: Status | G1: Date Sent | H1: Notes for Finance
A2: INV-38952AF | B2: =IFERROR(INDEX(Campaigns!$B$2:$B$10,MATCH("CMP-05",Campaigns!$A$2:$A$10,0)),"") -> Haas F1 Partnership | C2: CMP5-SOW1 | D2: Jan-26 | E2: =SUMIF('Monthly Recognition'!$F$2:$F$100,$A2,'Monthly Recognition'!$E$2:$E$100) -> 19500 | F2: Sent to Finance
A3: INV-38953AF | B3: =IFERROR(INDEX(Campaigns!$B$2:$B$10,MATCH("CMP-05",Campaigns!$A$2:$A$10,0)),"") -> Haas F1 Partnership | C3: CMP5-SOW1 | D3: Feb-26 / Apr-26 | E3: =SUMIF('Monthly Recognition'!$F$2:$F$100,$A3,'Monthly Recognition'!$E$2:$E$100) -> 44500 | F3: Sent to Finance | H3: Recognized across two months in source file — confirm with Finance this is one invoice.
A4: INV-39386AF | B4: =IFERROR(INDEX(Campaigns!$B$2:$B$10,MATCH("CMP-05",Campaigns!$A$2:$A$10,0)),"") -> Haas F1 Partnership | C4: CMP5-SOW1 | D4: Mar-26 | E4: =SUMIF('Monthly Recognition'!$F$2:$F$100,$A4,'Monthly Recognition'!$E$2:$E$100) -> 14500 | F4: Sent to Finance
A5: INV-39927AF | B5: =IFERROR(INDEX(Campaigns!$B$2:$B$10,MATCH("CMP-05",Campaigns!$A$2:$A$10,0)),"") -> Haas F1 Partnership | C5: CMP5-SOW1 | D5: Apr-26 | E5: =SUMIF('Monthly Recognition'!$F$2:$F$100,$A5,'Monthly Recognition'!$E$2:$E$100) -> 21500 | F5: Sent to Finance
A6: INV-40021AF | B6: =IFERROR(INDEX(Campaigns!$B$2:$B$10,MATCH("CMP-05",Campaigns!$A$2:$A$10,0)),"") -> Haas F1 Partnership | C6: CMP5-SOW1 | D6: May-26 | E6: =SUMIF('Monthly Recognition'!$F$2:$F$100,$A6,'Monthly Recognition'!$E$2:$E$100) -> 22500 | F6: Sent to Finance
A7: INV-40022AF | B7: =IFERROR(INDEX(Campaigns!$B$2:$B$10,MATCH("CMP-05",Campaigns!$A$2:$A$10,0)),"") -> Haas F1 Partnership | C7: CMP5-SOW1 | D7: Jun-26 | E7: =SUMIF('Monthly Recognition'!$F$2:$F$100,$A7,'Monthly Recognition'!$E$2:$E$100) -> 0 | F7: Not Yet Sent | H7: Not yet recognized — $15,000 open.
A8: INV-40023AF | B8: =IFERROR(INDEX(Campaigns!$B$2:$B$10,MATCH("CMP-05",Campaigns!$A$2:$A$10,0)),"") -> Haas F1 Partnership | C8: CMP5-SOW1 | D8: Jul-26 | E8: =SUMIF('Monthly Recognition'!$F$2:$F$100,$A8,'Monthly Recognition'!$E$2:$E$100) -> 0 | F8: Not Yet Sent | H8: Not yet recognized — $17,250 open.
A9: INV-40024AF | B9: =IFERROR(INDEX(Campaigns!$B$2:$B$10,MATCH("CMP-05",Campaigns!$A$2:$A$10,0)),"") -> Haas F1 Partnership | C9: CMP5-SOW1 | D9: Aug-26 | E9: =SUMIF('Monthly Recognition'!$F$2:$F$100,$A9,'Monthly Recognition'!$E$2:$E$100) -> 0 | F9: Not Yet Sent | H9: Not yet recognized — $21,500 open.
A10: INV-40025AF | B10: =IFERROR(INDEX(Campaigns!$B$2:$B$10,MATCH("CMP-05",Campaigns!$A$2:$A$10,0)),"") -> Haas F1 Partnership | C10: CMP5-SOW1 | D10: Sep-26 | E10: =SUMIF('Monthly Recognition'!$F$2:$F$100,$A10,'Monthly Recognition'!$E$2:$E$100) -> 0 | F10: Not Yet Sent | H10: Not yet recognized — $14,000 open.
A11: INV-40026AF | B11: =IFERROR(INDEX(Campaigns!$B$2:$B$10,MATCH("CMP-05",Campaigns!$A$2:$A$10,0)),"") -> Haas F1 Partnership | C11: CMP5-SOW1 | D11: Oct-26 | E11: =SUMIF('Monthly Recognition'!$F$2:$F$100,$A11,'Monthly Recognition'!$E$2:$E$100) -> 0 | F11: Not Yet Sent | H11: Not yet recognized — $14,000 open.
A12: INV-40027AF | B12: =IFERROR(INDEX(Campaigns!$B$2:$B$10,MATCH("CMP-05",Campaigns!$A$2:$A$10,0)),"") -> Haas F1 Partnership | C12: CMP5-SOW1 | D12: Nov-26 | E12: =SUMIF('Monthly Recognition'!$F$2:$F$100,$A12,'Monthly Recognition'!$E$2:$E$100) -> 0 | F12: Not Yet Sent | H12: Not yet recognized — $21,500 open.
A13: INV-40028AF | B13: =IFERROR(INDEX(Campaigns!$B$2:$B$10,MATCH("CMP-05",Campaigns!$A$2:$A$10,0)),"") -> Haas F1 Partnership | C13: CMP5-SOW1 | D13: Dec-26 | E13: =SUMIF('Monthly Recognition'!$F$2:$F$100,$A13,'Monthly Recognition'!$E$2:$E$100) -> 0 | F13: Not Yet Sent | H13: Not yet recognized — $21,500 open.
A14: INV-37370AF | B14: =IFERROR(INDEX(Campaigns!$B$2:$B$10,MATCH("CMP-07",Campaigns!$A$2:$A$10,0)),"") -> Comms AOR | C14: CMP7-SOW1 | D14: Mar-26 | E14: =SUMIF('Monthly Recognition'!$F$2:$F$100,$A14,'Monthly Recognition'!$E$2:$E$100) -> 60000 | F14: Sent to Finance
A15: INV-37371AF | B15: =IFERROR(INDEX(Campaigns!$B$2:$B$10,MATCH("CMP-07",Campaigns!$A$2:$A$10,0)),"") -> Comms AOR | C15: CMP7-SOW1 | D15: Apr-26 | E15: =SUMIF('Monthly Recognition'!$F$2:$F$100,$A15,'Monthly Recognition'!$E$2:$E$100) -> 60000 | F15: Sent to Finance
A16: INV-37372AF | B16: =IFERROR(INDEX(Campaigns!$B$2:$B$10,MATCH("CMP-07",Campaigns!$A$2:$A$10,0)),"") -> Comms AOR | C16: CMP7-SOW1 | D16: May-26 | E16: =SUMIF('Monthly Recognition'!$F$2:$F$100,$A16,'Monthly Recognition'!$E$2:$E$100) -> 60000 | F16: Sent to Finance
A17: INV-37373AF | B17: =IFERROR(INDEX(Campaigns!$B$2:$B$10,MATCH("CMP-07",Campaigns!$A$2:$A$10,0)),"") -> Comms AOR | C17: CMP7-SOW1 | D17: Jun-26 | E17: =SUMIF('Monthly Recognition'!$F$2:$F$100,$A17,'Monthly Recognition'!$E$2:$E$100) -> 0 | F17: Not Yet Sent | H17: Not yet recognized — $60,000 open.
A18: INV-39804AO | B18: =IFERROR(INDEX(Campaigns!$B$2:$B$10,MATCH("CMP-07",Campaigns!$A$2:$A$10,0)),"") -> Comms AOR | C18: CMP7-EXTRA1 | D18: Mar-26 | E18: =SUMIF('Monthly Recognition'!$F$2:$F$100,$A18,'Monthly Recognition'!$E$2:$E$100) -> 8874.92 | F18: Sent to Finance | H18: OOP Expenses.
A20: REVENUE WITH NO INVOICE # ASSIGNED YET
A21: =SUMIF('Monthly Recognition'!$F$2:$F$100,"Not yet assigned",'Monthly Recognition'!$E$2:$E$100) -> 1128873.9 | B21: Total recognized revenue across Brand Campaign Creative, Cancer Center Pavilion, U.S. News, Strategic Counsel, and part of Comms AOR that has never been tied to an invoice number. Assign invoice #s in Monthly Recognition column F to bring this to zero.
